<annotation>
	<folder>parking_spaces</folder>
	<filename>000037.png</filename>
	<path>/home/nathan/projects/machine_learning/tensorflow/projects/deep_parking/data/parking_spaces/000037.png</path>
	<source>
		<database>Unknown</database>
	</source>
	<size>
		<width>0</width>
		<height>0</height>
		<depth>3</depth>
	</size>
	<segmented>0</segmented>
	<object>
		<name>empyt_space</name>
		<pose>Unspecified</pose>
		<truncated>0</truncated>
		<difficult>0</difficult>
		<bndbox>
			<xmin>3</xmin>
			<ymin>1636</ymin>
			<xmax>3008</xmax>
			<ymax>2311</ymax>
		</bndbox>
	</object>
	<object>
		<name>empyt_space</name>
		<pose>Unspecified</pose>
		<truncated>0</truncated>
		<difficult>0</difficult>
		<bndbox>
			<xmin>19</xmin>
			<ymin>1373</ymin>
			<xmax>3008</xmax>
			<ymax>1761</ymax>
		</bndbox>
	</object>
	<object>
		<name>empyt_space</name>
		<pose>Unspecified</pose>
		<truncated>0</truncated>
		<difficult>0</difficult>
		<bndbox>
			<xmin>390</xmin>
			<ymin>1182</ymin>
			<xmax>2776</xmax>
			<ymax>1418</ymax>
		</bndbox>
	</object>
	<object>
		<name>empyt_space</name>
		<pose>Unspecified</pose>
		<truncated>0</truncated>
		<difficult>0</difficult>
		<bndbox>
			<xmin>658</xmin>
			<ymin>1082</ymin>
			<xmax>2503</xmax>
			<ymax>1259</ymax>
		</bndbox>
	</object>
	<object>
		<name>empyt_space</name>
		<pose>Unspecified</pose>
		<truncated>0</truncated>
		<difficult>0</difficult>
		<bndbox>
			<xmin>828</xmin>
			<ymin>993</ymin>
			<xmax>2351</xmax>
			<ymax>1116</ymax>
		</bndbox>
	</object>
	<object>
		<name>empyt_space</name>
		<pose>Unspecified</pose>
		<truncated>0</truncated>
		<difficult>0</difficult>
		<bndbox>
			<xmin>935</xmin>
			<ymin>939</ymin>
			<xmax>2244</xmax>
			<ymax>1036</ymax>
		</bndbox>
	</object>
	<object>
		<name>empyt_space</name>
		<pose>Unspecified</pose>
		<truncated>0</truncated>
		<difficult>0</difficult>
		<bndbox>
			<xmin>1003</xmin>
			<ymin>893</ymin>
			<xmax>2174</xmax>
			<ymax>980</ymax>
		</bndbox>
	</object>
</annotation>
