<annotation>
	<folder>parking_spaces</folder>
	<filename>000095.png</filename>
	<path>/home/nathan/projects/machine_learning/tensorflow/projects/deep_parking/data/parking_spaces/000095.png</path>
	<source>
		<database>Unknown</database>
	</source>
	<size>
		<width>0</width>
		<height>0</height>
		<depth>3</depth>
	</size>
	<segmented>0</segmented>
	<object>
		<name>empyt_space</name>
		<pose>Unspecified</pose>
		<truncated>0</truncated>
		<difficult>0</difficult>
		<bndbox>
			<xmin>583</xmin>
			<ymin>1266</ymin>
			<xmax>1260</xmax>
			<ymax>1390</ymax>
		</bndbox>
	</object>
	<object>
		<name>empyt_space</name>
		<pose>Unspecified</pose>
		<truncated>0</truncated>
		<difficult>0</difficult>
		<bndbox>
			<xmin>5</xmin>
			<ymin>1335</ymin>
			<xmax>657</xmax>
			<ymax>1464</ymax>
		</bndbox>
	</object>
	<object>
		<name>empyt_space</name>
		<pose>Unspecified</pose>
		<truncated>0</truncated>
		<difficult>0</difficult>
		<bndbox>
			<xmin>1202</xmin>
			<ymin>1488</ymin>
			<xmax>3114</xmax>
			<ymax>1840</ymax>
		</bndbox>
	</object>
	<object>
		<name>empyt_space</name>
		<pose>Unspecified</pose>
		<truncated>0</truncated>
		<difficult>0</difficult>
		<bndbox>
			<xmin>1741</xmin>
			<ymin>1412</ymin>
			<xmax>3248</xmax>
			<ymax>1674</ymax>
		</bndbox>
	</object>
	<object>
		<name>empyt_space</name>
		<pose>Unspecified</pose>
		<truncated>0</truncated>
		<difficult>0</difficult>
		<bndbox>
			<xmin>2086</xmin>
			<ymin>1369</ymin>
			<xmax>3264</xmax>
			<ymax>1535</ymax>
		</bndbox>
	</object>
	<object>
		<name>empyt_space</name>
		<pose>Unspecified</pose>
		<truncated>0</truncated>
		<difficult>0</difficult>
		<bndbox>
			<xmin>2336</xmin>
			<ymin>1328</ymin>
			<xmax>3264</xmax>
			<ymax>1449</ymax>
		</bndbox>
	</object>
	<object>
		<name>empyt_space</name>
		<pose>Unspecified</pose>
		<truncated>0</truncated>
		<difficult>0</difficult>
		<bndbox>
			<xmin>800</xmin>
			<ymin>1240</ymin>
			<xmax>1533</xmax>
			<ymax>1359</ymax>
		</bndbox>
	</object>
	<object>
		<name>empyt_space</name>
		<pose>Unspecified</pose>
		<truncated>0</truncated>
		<difficult>0</difficult>
		<bndbox>
			<xmin>1119</xmin>
			<ymin>1228</ymin>
			<xmax>1762</xmax>
			<ymax>1326</ymax>
		</bndbox>
	</object>
	<object>
		<name>empyt_space</name>
		<pose>Unspecified</pose>
		<truncated>0</truncated>
		<difficult>0</difficult>
		<bndbox>
			<xmin>1362</xmin>
			<ymin>1221</ymin>
			<xmax>1948</xmax>
			<ymax>1297</ymax>
		</bndbox>
	</object>
</annotation>
